cprunner/__init__.py
cprunner/__main__.py
cprunner/cprunner.py
cprunner-0.1.3.dist-info/LICENSE
cprunner-0.1.3.dist-info/METADATA
cprunner-0.1.3.dist-info/WHEEL
cprunner-0.1.3.dist-info/entry_points.txt
cprunner-0.1.3.dist-info/top_level.txt
cprunner-0.1.3.dist-info/RECORD
